{
    "home" : {
        "name" : "Gustavo Calonico", 
        "sub" : "Software Engineer at Rio de Janeiro, Brazil",
        "description": "Undergraduate software developer/engineer with 3 years experience on the market. Passionate about free open-source software, decentralized technologies and programming. Musician and drummer on my free time.",
        "sections" : {
            "projects": "Projects",
            "language": "Language",
            "gpg" : "GPG"
        },
        "footer" : {
            "contact" : "Contact",
            "media" : "Media"
        }
    },
    "error" : {
        "githubInfo": "Error loading Github info",
        "githubRepos": "Error loading Github repositories"
    },
    "languages": [
        { "key": "pt-br", "name": "Portuguese (Brazil)"       },
        { "key": "en-us", "name": "English (United States)"   }
    ]
}